[{"title": "Learn Hindi Through English - Lesson 1 - Are You Ready", "id": "mAWv8iEX7uw", "thumbnail": "https://i.ytimg.com/vi/mAWv8iEX7uw/default.jpg", "description": "Learn Hindi Through English - Lesson 1 - My Hindi Speaking Tutorial videos will be helpful you to learn to speak Hindi fluently like native speaker from English.", "topic": "Learn Learn Hindi"}, {"title": "WATCH & LEARN HINDI CONVERSATION VIDEOS WITH ENGLISH SUBTITLES (Lesson 1): THIS, THAT, ARE YOU ?", "id": "c2pwnHLaYTQ", "thumbnail": "https://i.ytimg.com/vi/c2pwnHLaYTQ/default.jpg", "description": "Watch & Learn Hindi Conversation videos with English subtitles given- Lesson 1 - In these basic Hindi conversation lessons, I will be talking in Hindi language ...", "topic": "Learn Learn Hindi"}]