[{"title": "SQL for Beginners. Learn basics  of SQL in 1 Hour", "id": "7Vtl2WggqOg", "thumbnail": "https://i.ytimg.com/vi/7Vtl2WggqOg/default.jpg", "description": "SQL is a special-purpose programming language designed for managing data in a relational database, and is used by a huge number of apps and ...", "topic": "Learn SQL Server"}, {"title": "Learn SQL Server step by step tutorial - Part 1  ( Beginner series)", "id": "o9D6G-LVp5U", "thumbnail": "https://i.ytimg.com/vi/o9D6G-LVp5U/default.jpg", "description": "In this video we will learn SQL Server step by step in 16 hours. See our other Step by Step video series below. Learn MSBI Step by Step in 32 hours:- ...", "topic": "Learn SQL Server"}]